{
  "id": "article-58-",
  "title": "Article 58 : Les associations et les organisations non gouvernementales légalement reconnues ne peuvent soutenir, ni tenir des propos visant à ternir l'image des candidats ou des partis politiques sous peine de déchéance de leur statut et des sanctions prévues au code pénal contre les personnes physiques en charge des associations ou organisations concernées.",
  "numero": "58 ",
  "document": "code-electoral",
  "path": [
    "livre-1",
    "titre-4"
  ],
  "navigation": {
    "parent": "titre-4",
    "previous": "article-57-",
    "next": "article-59-"
  }
}