{
  "id": "article-267-",
  "title": "Article 267 : Tout candidat aux élections du Président de la République, des membres de l’Assemblée Nationale ou des conseils communaux ou municipaux et des membres des conseils de village ou de quartier de ville, condamné à une peine de déchéance des droits civils et politiques est de plein droit frappé d’inéligibilité pour la durée de la condamnation et au cas où le vote est acquis, son élection est frappée d’invalidité.",
  "numero": "267 ",
  "document": "codepenalbenin",
  "path": [
    "livre-1",
    "chapitre-4"
  ],
  "navigation": {
    "parent": "chapitre-4",
    "previous": "article-266-",
    "next": "article-268-"
  }
}