{
  "id": "article-462-3-nouveau--loi-2022-37--",
  "title": "Article 462-3 nouveau (Loi 2022-37) : Est punie de deux (02) ans d'emprisonnement au maximum, l'absence non autorisée du corps pendant plus de trois (03) jours.",
  "numero": "462-3 nouveau (Loi 2022-37) ",
  "document": "codepenalbenin",
  "path": [
    "livre-1",
    "chapitre-7"
  ],
  "navigation": {
    "parent": "chapitre-7",
    "previous": "article-462-2-nouveau--loi-2022-37--",
    "next": "article-462-4-nouveau--loi-2022-37--"
  }
}