{
  "id": "article-49-",
  "title": "Article 49 : Lorsqu’elle est encourue à titre de peine complémentaire pour un crime ou un délit, l’interdiction d’exercer une fonction publique ou d’exercer une activité professionnelle ou sociale est soit définitive, soit temporaire ; dans ce dernier cas, elle ne peut excéder une durée de cinq (05) ans.",
  "numero": "49 ",
  "document": "codepenalbenin",
  "path": [
    "livre-1",
    "section-1",
    "paragraphe-4"
  ],
  "navigation": {
    "parent": "paragraphe-4",
    "previous": "article-48-",
    "next": "article-50-"
  }
}