{
  "id": "article-285-nouveau--loi-n--2025---06--",
  "title": "Article 285 nouveau (LOI N° 2025 – 06) : L'accusé ne cesse pas de pouvoir communiquer librement avec son avocat. Celui-ci peut prendre sur place communication de toutes les pièces sans que cette communication puisse provoquer un retard dans le déroulement de la procédure.",
  "numero": "285 nouveau (LOI N° 2025 – 06) ",
  "document": "codeprocedurepenalbenin",
  "path": [
    "livre-2"
  ],
  "navigation": {
    "parent": "livre-2",
    "previous": "article-285-ancien-",
    "next": "article-286-"
  }
}