{
  "id": "article-117-nouveau--loi-n-2021-13--",
  "title": "Article 117 nouveau (LOI N°2021-13) : « La convention est passée en présence de deux témoins au moins pour chaque fiancé et d'un représentant de chaque famille. Les fiancés peuvent s'offrir réciproquement des présents.",
  "numero": "117 nouveau (LOI N°2021-13) ",
  "document": "coode-personnes-familles",
  "path": [
    "livre-2"
  ],
  "navigation": {
    "parent": "livre-2",
    "previous": "article-117-ancien-",
    "next": "article-118-ancien-"
  }
}