{
  "id": "article-664-",
  "title": "Article 664 : Sans préjudice des autres peines complémentaires applicables aux délits selon le droit commun, les personnes visées à l’article précédent pourront en outre être interdites, par le tribunal, pour une durée n’excédant pas cinq (05) ans, de diriger, administrer ou gérer :",
  "numero": "664 ",
  "document": "codepenalbenin",
  "path": [
    "livre-1"
  ],
  "navigation": {
    "parent": "livre-1",
    "previous": "article-663-",
    "next": "article-665-"
  }
}