{
  "id": "article-810-1--loi-n--2022-19--",
  "title": "Article 810-1 (LOI N° 2022-19) : En toute matière, les condamnés à une peine privative de liberté passée en force de chose jugée peuvent bénéficier d'une suspension de l'exécution de leur peine si l’exécution a été entamée et qu'il est établi à leur égard des circonstances de nature à justifier cette mesure.",
  "numero": "810-1 (LOI N° 2022-19) ",
  "document": "codeprocedurepenalbenin",
  "path": [
    "livre-5"
  ],
  "navigation": {
    "parent": "livre-5",
    "previous": "article-810-",
    "next": "article-810-2--loi-n--2022-19--"
  }
}